{"UI":true,"UIcameraControls":true,"UIcolorPicker":{"All":true,"IP":true,"ruler":true,"disk":true,"EP":true,"NEP":true},"UIdecimation":true,"UIdropdown":{"All":true,"IP":true,"ruler":true,"disk":true,"EP":true,"NEP":true},"UIfullscreen":true,"UIloadNewData":true,"UIparticle":{"All":true,"IP":true,"ruler":true,"disk":true,"EP":true,"NEP":true},"UIreset":true,"UIsavePreset":true,"UIsnapshot":true,"camera":null,"cameraRotation":null,"center":[0.0,0.0,0.0],"color":{"All":[1.0,1.0,1.0,1.0],"IP":[0.2980392157,0.6862745098,0.0,1.0],"ruler":[0.9744040384,0.0604181573,0.5333513674,1.0],"disk":[0.0011451185,0.9280747919,0.8014313733,1.0],"EP":[0.7,0.46984,0.196,1.0],"NEP":[0.196,0.532,0.7,1.0]},"colormapLims":{"All":{},"IP":{},"ruler":{},"disk":{},"EP":{},"NEP":{}},"colormapVals":{"All":{},"IP":{},"ruler":{},"disk":{},"EP":{},"NEP":{}},"decimate":null,"filterLims":{"All":{"is_in_main_gal":null,"logT":null,"logZ":null,"PType":null,"is_in_other_gal":null,"logDen":null},"IP":{"is_in_main_gal":null,"logT":null,"logZ":null,"PType":null,"is_in_other_gal":null,"logDen":null},"ruler":{},"disk":{},"EP":{"is_in_main_gal":null,"logT":null,"logZ":null,"PType":null,"is_in_other_gal":null,"logDen":null},"NEP":{"is_in_main_gal":null,"logT":null,"logZ":null,"PType":null,"is_in_other_gal":null,"logDen":null}},"filterVals":{"All":{"is_in_main_gal":null,"logT":null,"logZ":null,"PType":null,"is_in_other_gal":null,"logDen":null},"IP":{"is_in_main_gal":null,"logT":null,"logZ":null,"PType":null,"is_in_other_gal":null,"logDen":null},"ruler":{},"disk":{},"EP":{"is_in_main_gal":null,"logT":null,"logZ":null,"PType":null,"is_in_other_gal":null,"logDen":null},"NEP":{"is_in_main_gal":null,"logT":null,"logZ":null,"PType":null,"is_in_other_gal":null,"logDen":null}},"friction":null,"loaded":true,"maxVrange":2000.0,"plotNmax":{"All":null,"IP":null,"ruler":null,"disk":null,"EP":null,"NEP":null},"showParts":{"All":true,"IP":true,"ruler":true,"disk":true,"EP":true,"NEP":true},"showVel":{"All":false,"IP":false,"ruler":false,"disk":false,"EP":false,"NEP":false},"sizeMult":{"All":1.0,"IP":1.0,"ruler":1.0,"disk":1.0,"EP":1.0,"NEP":1.0},"startFly":false,"stereo":false,"stereoSep":null,"title":"Firefly","velType":{"All":null,"IP":null,"ruler":null,"disk":null,"EP":null,"NEP":null}}